sentence_plagiarism/__init__.py
sentence_plagiarism/cli.py
sentence_plagiarism/plagiarism_checker.py
sentence_plagiarism/similarity.py
sentence_plagiarism/visualization/__init__.py
sentence_plagiarism/visualization/file_handlers.py
sentence_plagiarism/visualization/html_generator.py
sentence_plagiarism/visualization/models.py
sentence_plagiarism/visualization/templates/plagiarism_report.css
sentence_plagiarism/visualization/templates/plagiarism_report.js
sentence_plagiarism/visualization/templates/plagiarism_report_template.html
sentence_plagiarism/visualization/text_processing.py
sentence_plagiarism/visualization/visualization_utils.py
sentence_plagiarism/visualization/visualizer.py
sentence_plagiarism-0.8.0.dist-info/LICENSE
sentence_plagiarism-0.8.0.dist-info/METADATA
sentence_plagiarism-0.8.0.dist-info/WHEEL
sentence_plagiarism-0.8.0.dist-info/entry_points.txt
sentence_plagiarism-0.8.0.dist-info/RECORD
