Metadata-Version: 2.3
Name: sentence-plagiarism
Version: 0.8.0
Summary: Compare sentences from input document with all sentences from reference documents - find very similar ones.
License: MIT
Keywords: plagiarism,plagiarism-detection,text-similarity,sentence_similarity,sentence-plagiarism
Author: Krystian Safjan
Author-email: ksafjan@gmail.com
Requires-Python: >=3.9,<4.0
Classifier: License :: OSI Approved :: MIT License
Classifier: Programming Language :: Python :: 3
Classifier: Programming Language :: Python :: 3.9
Classifier: Programming Language :: Python :: 3.10
Classifier: Programming Language :: Python :: 3.11
Classifier: Programming Language :: Python :: 3.12
Classifier: Programming Language :: Python :: 3.13
Requires-Dist: beautifulsoup4 (>=4.13.4,<5.0.0)
Requires-Dist: markdown[extra] (>=3.8,<4.0)
Project-URL: Documentation, https://github.com/izikeros/sentence-plagiarism
Project-URL: Homepage, https://github.com/izikeros/sentence-plagiarism
Project-URL: Repository, https://github.com/izikeros/sentence-plagiarism
